cryoet_alignment/__init__.py
cryoet_alignment/api/__init__.py
cryoet_alignment/api/read.py
cryoet_alignment/api/write.py
cryoet_alignment/io/__init__.py
cryoet_alignment/io/base.py
cryoet_alignment/io/aretomo3/__init__.py
cryoet_alignment/io/aretomo3/aln.py
cryoet_alignment/io/cryoet_data_portal/__init__.py
cryoet_alignment/io/cryoet_data_portal/alignment.py
cryoet_alignment/io/imod/ImodAlignment.py
cryoet_alignment/io/imod/__init__.py
cryoet_alignment/io/imod/newst.py
cryoet_alignment/io/imod/rawtlt.py
cryoet_alignment/io/imod/tilt.py
cryoet_alignment/io/imod/xf.py
cryoet_alignment/util/__init__.py
cryoet_alignment/util/image.py
cryoet_alignment-0.1.1.dist-info/METADATA
cryoet_alignment-0.1.1.dist-info/WHEEL
cryoet_alignment-0.1.1.dist-info/licenses/LICENSE
cryoet_alignment-0.1.1.dist-info/RECORD
