Metadata-Version: 2.4
Name: cryoet_alignment
Version: 0.1.1
Summary: Alignment format conversion for cryoET.
Project-URL: Repository, https://github.com/uermel/cryoet-alignment.git
Project-URL: Issues, https://github.com/uermel/cryoet-alignment/issues
Author-email: "Utz H. Ermel" <utz.ermel@czii.org>
License: MIT License
License-File: LICENSE
Keywords: alignment,cryo-et,cryoet,tomography
Classifier: Development Status :: 3 - Alpha
Classifier: License :: OSI Approved :: MIT License
Requires-Python: >=3.9
Requires-Dist: click
Requires-Dist: cryoet-data-portal>=4.3.1
Requires-Dist: fsspec>=2024.6.0
Requires-Dist: mrcfile
Requires-Dist: numpy
Requires-Dist: pandas
Requires-Dist: pydantic>=2
Requires-Dist: s3fs
Provides-Extra: cdp
Requires-Dist: cryoet-data-portal>=4.3.1; extra == 'cdp'
Requires-Dist: zarr; extra == 'cdp'
Provides-Extra: dev
Requires-Dist: black; extra == 'dev'
Requires-Dist: ipython; extra == 'dev'
Requires-Dist: notebook; extra == 'dev'
Requires-Dist: pre-commit; extra == 'dev'
Requires-Dist: ruff; extra == 'dev'
Provides-Extra: docs
Requires-Dist: mkdocs; extra == 'docs'
Requires-Dist: mkdocs-autorefs; extra == 'docs'
Requires-Dist: mkdocs-material; extra == 'docs'
Requires-Dist: mkdocstrings[python]; extra == 'docs'
Provides-Extra: test
Requires-Dist: pytest; extra == 'test'
Requires-Dist: pytest-cov; extra == 'test'
